{
  "Version": "2012-10-17",
  "Statement": [
      {
          "Effect": "Allow",
          "Action": [
              "ec2:CreateTags",
              "ec2:DeleteInternetGateway",
              "ec2:DeleteNatGateway",
              "ec2:DeleteSecurityGroup",
              "ec2:DeleteSubnet",
              "ec2:DeleteRouteTable",
              "ec2:DeleteVpc",
              "ec2:DisassociateRouteTable",
              "ec2:DescribeAddresses",
              "ec2:DescribeAvailabilityZones",
	      "ec2:DescribeDhcpOptions",
              "ec2:DescribeImages",
              "ec2:DescribeInstances",
              "ec2:DescribeInstanceTypes",
              "ec2:DescribeInternetGateways",
              "ec2:DescribeNatGateways",
              "ec2:DescribeNetworkInterfaces",
              "ec2:DescribeRegions",
              "ec2:DescribeRouteTables",
              "ec2:DescribeSecurityGroups",
              "ec2:DescribeSubnets",
              "ec2:DescribeVpcs",
              "ec2:DetachInternetGateway",
              "ec2:ModifyNetworkInterfaceAttribute",
              "ec2:ReleaseAddress",
              "ec2:RunInstances",
              "ec2:TerminateInstances",
              "ecr:GetAuthorizationToken",
              "eks:CreateCluster",
              "eks:DescribeAddon",
              "eks:DescribeAddonVersions",
              "eks:UpdateAddon",
              "iam:ListOpenIDConnectProviders"
          ],
          "Resource": "*"
      },
      {
          "Effect": "Allow",
          "Action": [
              "ec2:AllocateAddress",
              "ec2:AssociateRouteTable",
	          "ec2:AssociateVpcCidrBlock",
              "ec2:AttachInternetGateway",
              "ec2:CreateVpc",
              "ec2:CreateRoute",
              "ec2:CreateRouteTable",
              "ec2:CreateSubnet",
              "ec2:CreateInternetGateway",
              "ec2:CreateNatGateway",
              "ec2:CreateSecurityGroup",
              "ec2:DescribeVpcAttribute",
              "ec2:DisassociateVpcCidrBlock",
              "ec2:ModifySubnetAttribute",
              "ec2:ModifyVpcAttribute",
              "ecr:BatchCheckLayerAvailability",
              "ecr:BatchGetImage",
              "ecr:ListImages",
              "ecr:GetDownloadUrlForLayer",
              "eks:DescribeCluster",
              "eks:CreateAddon",
              "eks:DeleteCluster",
              "eks:ListAddons",
              "eks:TagResource",
              "eks:UpdateClusterConfig",
              "eks:UpdateClusterVersion",
              "secretsmanager:CreateSecret",
              "secretsmanager:DeleteSecret",
              "secretsmanager:TagResource"
          ],
          "Resource": [
              "arn:aws:secretsmanager:*:${AWS_ACCOUNT_ID}:secret:aws.cluster.x-k8s.io/*",
              "arn:aws:ec2:*:${AWS_ACCOUNT_ID}:elastic-ip/*",
              "arn:aws:ec2:*:${AWS_ACCOUNT_ID}:internet-gateway/*",
              "arn:aws:ec2:*:${AWS_ACCOUNT_ID}:natgateway/*",
              "arn:aws:ec2:*:${AWS_ACCOUNT_ID}:route-table/*",
              "arn:aws:ec2:*:${AWS_ACCOUNT_ID}:security-group/*",
              "arn:aws:ec2:*:${AWS_ACCOUNT_ID}:subnet/*",
              "arn:aws:ec2:*:${AWS_ACCOUNT_ID}:vpc/*",
              "arn:aws:ecr:*:*:repository/*",
              "arn:aws:eks:*:${AWS_ACCOUNT_ID}:addon/*",
              "arn:aws:eks:*:${AWS_ACCOUNT_ID}:cluster/*"
          ]
      },
      {
          "Effect": "Allow",
          "Action": [
              "ec2:AuthorizeSecurityGroupIngress"
          ],
          "Resource": [
              "arn:aws:ec2:*:${AWS_ACCOUNT_ID}:security-group/*"
          ]
      },
      {
          "Effect": "Allow",
          "Action": [
              "ssm:GetParameter"
          ],
          "Resource": [
              "arn:*:ssm:*:*:parameter/aws/service/eks/optimized-ami/*"
          ]
      },
      {
          "Effect": "Allow",
          "Action": [
              "iam:CreateOpenIDConnectProvider",
              "iam:DeleteOpenIDConnectProvider",
              "iam:GetOpenIDConnectProvider",
              "iam:TagOpenIDConnectProvider",
              "iam:ListAttachedRolePolicies",
              "iam:CreateRole",
              "iam:TagRole",
              "iam:UntagRole"
          ],
          "Resource": [
              "arn:aws:iam::${AWS_ACCOUNT_ID}:role/*",
              "arn:aws:iam::${AWS_ACCOUNT_ID}:oidc-provider/*"
          ]
      },
      {
          "Sid": "CAPALaunchTemplates",
          "Effect": "Allow",
          "Action": [
              "ec2:CreateLaunchTemplate",
              "ec2:CreateLaunchTemplateVersion",
              "ec2:DescribeLaunchTemplates",
              "ec2:DescribeLaunchTemplateVersions",
              "ec2:DeleteLaunchTemplate",
              "ec2:DeleteLaunchTemplateVersions",
              "ec2:DescribeKeyPairs",
              "eks:TagResource",
              "eks:UntagResource",
              "eks:UpdateNodegroupConfig",
              "iam:TagRole",
              "iam:UntagRole"
          ],
          "Resource": "*"
      },
      {
          "Sid": "CAPAAutoScalingGroups",
          "Effect": "Allow",
          "Action": [
              "autoscaling:CreateAutoScalingGroup",
              "autoscaling:UpdateAutoScalingGroup",
              "autoscaling:CreateOrUpdateTags",
              "autoscaling:StartInstanceRefresh",
              "autoscaling:DeleteAutoScalingGroup",
              "autoscaling:DeleteTags"
          ],
          "Resource": "arn:aws:autoscaling:*:${AWS_ACCOUNT_ID}:autoScalingGroup:*:autoScalingGroupName/*"
      }
  ]
}
